lexibase/__init__.py
lexibase/lexibase.py
lexibase/util.py
lexibase-0.1.0.dist-info/LICENSE.txt
lexibase-0.1.0.dist-info/METADATA
lexibase-0.1.0.dist-info/RECORD
lexibase-0.1.0.dist-info/WHEEL
lexibase-0.1.0.dist-info/entry_points.txt
lexibase-0.1.0.dist-info/top_level.txt
